lightspeed/__about__.py
lightspeed/__init__.py
lightspeed/exceptions.py
lightspeed/oracle.py
lightspeed_oracle-0.0.1.dist-info/METADATA
lightspeed_oracle-0.0.1.dist-info/WHEEL
lightspeed_oracle-0.0.1.dist-info/licenses/LICENSE.txt
lightspeed_oracle-0.0.1.dist-info/RECORD
