Metadata-Version: 2.4
Name: lightspeed-oracle
Version: 0.0.1
Summary: Lightweight, lightning-speed library for seamless retrieval of analysis-ready Binance spot market data
Project-URL: Documentation, https://github.com/traverne/lightspeed#readme
Project-URL: Issues, https://github.com/traverne/lightspeed/issues
Project-URL: Source, https://github.com/traverne/lightspeed
Author-email: Athen Traverne <athen@aetherionresearch.com>
License-Expression: MIT
License-File: LICENSE.txt
Classifier: Development Status :: 4 - Beta
Classifier: Programming Language :: Python
Classifier: Programming Language :: Python :: 3.9
Classifier: Programming Language :: Python :: 3.10
Classifier: Programming Language :: Python :: 3.11
Classifier: Programming Language :: Python :: 3.12
Classifier: Programming Language :: Python :: 3.13
Classifier: Programming Language :: Python :: 3.14
Classifier: Programming Language :: Python :: Implementation :: CPython
Classifier: Programming Language :: Python :: Implementation :: PyPy
Requires-Python: >=3.9
Requires-Dist: httpx
Requires-Dist: orjson
Requires-Dist: pandas
Requires-Dist: websocket
